__init__.py
core.py
env.py
evaluator.py
mal_types.py
parser.py
printer.py
stepA_mal.py
mal_python/__init__.py
mal_python/core.py
mal_python/env.py
mal_python/evaluator.py
mal_python/mal_types.py
mal_python/parser.py
mal_python/printer.py
mal_python/stepA_mal.py
mal_python-1.2.dist-info/DESCRIPTION.rst
mal_python-1.2.dist-info/METADATA
mal_python-1.2.dist-info/RECORD
mal_python-1.2.dist-info/WHEEL
mal_python-1.2.dist-info/entry_points.txt
mal_python-1.2.dist-info/metadata.json
mal_python-1.2.dist-info/top_level.txt
